{
    "apiVersion": "v1",
    "data": {
        "security.user.name": "dXNlcg==",
        "security.user.password": "dGVzdA=="
    },
    "kind": "Secret",
    "metadata": {
        "annotations": {
            "template.openshift.io/base64-expose-password": "{.data['security\\.user\\.password']}"
        },
        "labels": {
            "app": "jenkins",
            "project": "jenkins",
            "template": "jenkins"
        },
        "name": "temperature-conversion-credentials",
        "namespace": "jenkins"
    },
    "type": "Opaque"
}
